setup.py
stlee_test_distr/Binomialdistribution.py
stlee_test_distr/Gaussiandistribution.py
stlee_test_distr/Generaldistribution.py
stlee_test_distr/__init__.py
stlee_test_distr.egg-info/PKG-INFO
stlee_test_distr.egg-info/SOURCES.txt
stlee_test_distr.egg-info/dependency_links.txt
stlee_test_distr.egg-info/not-zip-safe
stlee_test_distr.egg-info/top_level.txt