Metadata-Version: 1.0
Name: stlee-test-distr
Version: 0.1
Summary: Gaussian and Binomial distr.
Home-page: UNKNOWN
Author: stlee
Author-email: myemail@testmail.com
License: UNKNOWN
Platform: UNKNOWN
